filabel/__init__.py
filabel/__main__.py
filabel/cli.py
filabel/logic.py
filabel/utils.py
filabel/web.py
filabel/static/style.css
filabel/templates/infopage.html
filabel/templates/layout.html
filabel_marekreimer-0.6.dist-info/LICENSE
filabel_marekreimer-0.6.dist-info/METADATA
filabel_marekreimer-0.6.dist-info/WHEEL
filabel_marekreimer-0.6.dist-info/entry_points.txt
filabel_marekreimer-0.6.dist-info/top_level.txt
filabel_marekreimer-0.6.dist-info/RECORD
