Metadata-Version: 2.1
Name: filabel-marekreimer
Version: 0.6
Summary: Simple CLI & WEB tool for labeling GitHub PRs using globs
Home-page: https://github.com/marekreimer/filabel
Author: Marek Suchánek, Marek Reimer
Author-email: suchama4@fit.cvut.cz, reimemar@fit.cvut.cz
License: MIT
Keywords: github labels management pull-requests globs
Platform: UNKNOWN
Classifier: Development Status :: 4 - Beta
Classifier: Environment :: Console
Classifier: Environment :: Web Environment
Classifier: Framework :: Flask
Classifier: Intended Audience :: Developers
Classifier: Intended Audience :: Education
Classifier: Intended Audience :: Information Technology
Classifier: Intended Audience :: Science/Research
Classifier: License :: OSI Approved :: MIT License
Classifier: Natural Language :: English
Classifier: Programming Language :: Python
Classifier: Programming Language :: Python :: 3
Classifier: Programming Language :: Python :: 3.6
Classifier: Programming Language :: Python :: 3.7
Classifier: Topic :: Software Development
Classifier: Topic :: Utilities
Requires-Dist: click
Requires-Dist: Flask
Requires-Dist: jinja2
Requires-Dist: requests
Requires-Dist: aiohttp
